mixpanel/__init__.py
mixpanel/context_processors.py
mixpanel/models.py
mixpanel/tasks.py
mixpanel/conf/__init__.py
mixpanel/conf/settings.py
testproj/__init__.py
testproj/manage.py
testproj/settings.py
testproj/urls.py
mixpanel_celery-0.10.1.dist-info/AUTHORS
mixpanel_celery-0.10.1.dist-info/LICENSE
mixpanel_celery-0.10.1.dist-info/METADATA
mixpanel_celery-0.10.1.dist-info/WHEEL
mixpanel_celery-0.10.1.dist-info/top_level.txt
mixpanel_celery-0.10.1.dist-info/RECORD
