Metadata-Version: 2.1
Name: mixpanel-celery
Version: 0.10.1
Summary: Asynchronous event tracking for Mixpanel
Home-page: http://winhamwr.github.io/mixpanel-celery/
Author: Wes Winham
Author-email: winhamwr@gmail.com
License: BSD
Platform: any
Classifier: Development Status :: 4 - Beta
Classifier: Framework :: Django
Classifier: Intended Audience :: Developers
Classifier: License :: OSI Approved :: BSD License
Classifier: Operating System :: POSIX
Classifier: Programming Language :: Python
Classifier: Programming Language :: Python :: 2.6
Classifier: Programming Language :: Python :: 2.7
Classifier: Programming Language :: Python :: 3.3
Classifier: Programming Language :: Python :: 3.4
Classifier: Programming Language :: Python :: 3.5
Classifier: Topic :: Internet
Classifier: Topic :: Software Development :: Libraries :: Python Modules
Requires-Dist: celery (>=2.5)
Requires-Dist: six
